{
  "metadata": {
    "id": "timeliness--contract-procedure"
  },
  "charts": [
    {
      "id": "average-timeline",
      "title": "Average Timeline",
      "x": {
        "label": "Contract procedure"
      },
      "y": {
        "label": "Days"
      },
      "data": [
        {
          "label": "Direct award",
          "data": [
            32,
            50,
            21
          ]
        },
        {
          "label": "Open call",
          "data": [
            80,
            20,
            33
          ]
        }
      ]
    }
  ]
}
